[
  {
    "name": "EquipmentDescription",
    "slots": [
      {
        "name": "equipment",
        "type": "Equipment"
      }
    ],
    "samples": [
      "what is {equipment}"
    ]
  },
  {
    "name": "EquipmentCost",
    "slots": [
      {
        "name": "equipment",
        "type": "Equipment"
      }
    ],
    "samples": [
      "how much does {equipment} cost"
    ]
  },
  {
    "name": "EquipmentWeight",
    "slots": [
      {
        "name": "equipment",
        "type": "Equipment"
      }
    ],
    "samples": [
      "how much does {equipment} weigh"
    ]
  }
]